modm_devices/__init__.py
modm_devices/device.py
modm_devices/device_file.py
modm_devices/device_identifier.py
modm_devices/exception.py
modm_devices/parser.py
modm_devices/pkg.py
modm_devices/resources/catalog.xml
modm_devices/resources/devices/db.json
modm_devices/resources/devices/avr/at90-32_64_128-can.xml
modm_devices/resources/devices/avr/atmega-128-rfa1.xml
modm_devices/resources/devices/avr/atmega-1281_2561.xml
modm_devices/resources/devices/avr/atmega-1284-n_p.xml
modm_devices/resources/devices/avr/atmega-164_324_644-a_n_p_pa_pv_v.xml
modm_devices/resources/devices/avr/atmega-169_329_649.xml
modm_devices/resources/devices/avr/atmega-16_32-u4_u4rc.xml
modm_devices/resources/devices/avr/atmega-16_32_64-c1_m1.xml
modm_devices/resources/devices/avr/atmega-324-pb.xml
modm_devices/resources/devices/avr/atmega-48_88_168_328-a_n_p_pa_pv_v.xml
modm_devices/resources/devices/avr/atmega-48_88_168_328-pb.xml
modm_devices/resources/devices/avr/atmega-640_1280_2560.xml
modm_devices/resources/devices/avr/atmega-64_128-a_l_n.xml
modm_devices/resources/devices/avr/atmega-8_16_32-a_l_n.xml
modm_devices/resources/devices/avr/atmega-8_16_32-u2.xml
modm_devices/resources/devices/avr/attiny-102_104.xml
modm_devices/resources/devices/avr/attiny-13.xml
modm_devices/resources/devices/avr/attiny-20.xml
modm_devices/resources/devices/avr/attiny-24_44_84.xml
modm_devices/resources/devices/avr/attiny-25_45_85.xml
modm_devices/resources/devices/avr/attiny-261_461_861.xml
modm_devices/resources/devices/avr/attiny-40.xml
modm_devices/resources/devices/avr/attiny-441_841.xml
modm_devices/resources/devices/avr/attiny-48_88.xml
modm_devices/resources/devices/avr/attiny-4_5_9_10.xml
modm_devices/resources/devices/nrf/nrf52810.xml
modm_devices/resources/devices/nrf/nrf52811.xml
modm_devices/resources/devices/nrf/nrf52820.xml
modm_devices/resources/devices/nrf/nrf52832.xml
modm_devices/resources/devices/nrf/nrf52833.xml
modm_devices/resources/devices/nrf/nrf52840.xml
modm_devices-0.12.1.dist-info/licenses/LICENSE
modm_devices-0.12.1.dist-info/METADATA
modm_devices-0.12.1.dist-info/WHEEL
modm_devices-0.12.1.dist-info/top_level.txt
modm_devices-0.12.1.dist-info/RECORD
