Metadata-Version: 2.4
Name: modm-devices
Version: 0.12.1
Summary: Curated data for AVR and ARM Cortex-M devices
Home-page: https://github.com/modm-io/modm-devices
Author: Niklas Hauser
Author-email: niklas@salkinium.com
License: MPL-2.0
Keywords: modm lbuild modm-devices stm32 avr sam nrf
Classifier: Development Status :: 3 - Alpha
Classifier: Environment :: Console
Classifier: Intended Audience :: Developers
Classifier: License :: OSI Approved :: BSD License
Classifier: Natural Language :: English
Classifier: Operating System :: OS Independent
Classifier: Programming Language :: Python
Classifier: Programming Language :: Python :: 3
Classifier: Topic :: Database
Classifier: Topic :: Software Development
Classifier: Topic :: Software Development :: Code Generators
Classifier: Topic :: Software Development :: Embedded Systems
Requires-Python: >=3.9.0
License-File: LICENSE
Requires-Dist: lxml
Dynamic: author
Dynamic: author-email
Dynamic: classifier
Dynamic: description
Dynamic: description-content-type
Dynamic: home-page
Dynamic: keywords
Dynamic: license
Dynamic: license-file
Dynamic: requires-dist
Dynamic: requires-python
Dynamic: summary
